jsonrpc2-0.4.1.dist-info/WHEEL
jsonrpc2-0.4.1.dist-info/entry_points.txt
jsonrpc2-0.4.1.dist-info/metadata.json
jsonrpc2-0.4.1.dist-info/METADATA
jsonrpc2-0.4.1.dist-info/top_level.txt
jsonrpc2-0.4.1.dist-info/DESCRIPTION.rst
jsonrpc2-0.4.1.dist-info/RECORD
jsonrpc2/gae.py
jsonrpc2/cmd.py
jsonrpc2/__init__.py
jsonrpc2/paste/__init__.py
jsonrpc2/paste/templates/__init__.py
jsonrpc2/paste/templates/paster_jsonrpc2_template/setup.py_tmpl
jsonrpc2/paste/templates/paster_jsonrpc2_template/run.ini_tmpl
jsonrpc2/paste/templates/paster_jsonrpc2_template/setup.cfg
jsonrpc2/paste/templates/paster_jsonrpc2_template/static/json2.js
jsonrpc2/paste/templates/paster_jsonrpc2_template/static/index.html_tmpl
jsonrpc2/paste/templates/paster_jsonrpc2_template/+package+/sample.py
jsonrpc2/paste/templates/paster_jsonrpc2_template/+package+/__init__.py
