Metadata-Version: 2.0
Name: jsonrpc2
Version: 0.4.1
Summary: WSGI Framework for JSON RPC 2.0
Home-page: http://hg.aodag.jp/jsonrpc2/
Author: Atsushi Odagiri
Author-email: aodagx@gmail.com
License: MIT
Keywords: wsgi request web http json rpc
Platform: UNKNOWN
Classifier: Intended Audience :: Developers
Classifier: License :: OSI Approved :: MIT License
Classifier: Topic :: Internet :: WWW/HTTP :: WSGI
Classifier: Topic :: Internet :: WWW/HTTP :: WSGI :: Application
Classifier: Programming Language :: Python :: 2.6
Classifier: Programming Language :: Python :: 2.7
Classifier: Programming Language :: Python :: 3
Classifier: Programming Language :: Python :: 3.2
Classifier: Programming Language :: Python :: 3.3
Classifier: Programming Language :: Python :: 3.4
Requires-Dist: six
Provides-Extra: PASTE
Requires-Dist: PasteScript; extra == 'PASTE'
Provides-Extra: test
Requires-Dist: pytest; extra == 'test'
Requires-Dist: pytest-cov; extra == 'test'
Requires-Dist: WebTest; extra == 'test'
